{
    "items": [
        {
            "id": "1",
            "title": "Yeni Sezon: Radiant Wilds Güncellemesi",
            "content": "Albion Online yeni sezonu ile birlikte yeni haritalar, ekipmanlar ve oyun mekanikleri ekledi. Oyuncular artık yeni Radiant Wilds bölgesinde maceralarına devam edebilir.",
            "date": "2026-03-27T00:00:00.000Z",
            "category": "update",
            "image": null
        },
        {
            "id": "2",
            "title": "Dragon Güncellemesi Geliyor",
            "content": "Yeni dragon bossları ve dragon themed ekipmanlar yakında oyuna ekleniyor. Guildlerinizle birlikte bu zorlu düşmanlara karşı savaşa hazır olun!",
            "date": "2026-03-26T00:00:00.000Z",
            "category": "update",
            "image": null
        },
        {
            "id": "3",
            "title": "Crafting Değişiklikleri",
            "content": "Yeni crafting sistemi ile birlikte bazı tarifler güncellendi. Artık focus kullanımı daha verimli hale getirildi.",
            "date": "2026-03-25T00:00:00.000Z",
            "category": "guide",
            "image": null
        }
    ],
    "lastUpdate": "2026-03-27T00:00:00.000Z"
}
